{
  "date_range": {
    "start": "2025-03-21",
    "end": "2025-03-25"
  },
  "summary": {
    "total_dates": 5,
    "passed": 5,
    "failed": 0,
    "errors": 0,
    "pass_rate": 100.0
  },
  "reports": [
    {
      "date": "2025-03-21",
      "status": "PASS",
      "source_boat_count": 7,
      "database_boat_count": 7,
      "matches": 7,
      "mismatches": [],
      "missing_boats": [],
      "extra_boats": [],
      "field_errors": [],
      "timestamp": "2025-10-17T03:28:31.308137"
    },
    {
      "date": "2025-03-22",
      "status": "PASS",
      "source_boat_count": 9,
      "database_boat_count": 9,
      "matches": 9,
      "mismatches": [],
      "missing_boats": [],
      "extra_boats": [],
      "field_errors": [],
      "timestamp": "2025-10-17T03:28:34.063814"
    },
    {
      "date": "2025-03-23",
      "status": "PASS",
      "source_boat_count": 8,
      "database_boat_count": 8,
      "matches": 8,
      "mismatches": [],
      "missing_boats": [],
      "extra_boats": [],
      "field_errors": [],
      "timestamp": "2025-10-17T03:28:36.778571"
    },
    {
      "date": "2025-03-24",
      "status": "PASS",
      "source_boat_count": 5,
      "database_boat_count": 5,
      "matches": 5,
      "mismatches": [],
      "missing_boats": [],
      "extra_boats": [],
      "field_errors": [],
      "timestamp": "2025-10-17T03:28:39.530379"
    },
    {
      "date": "2025-03-25",
      "status": "PASS",
      "source_boat_count": 3,
      "database_boat_count": 3,
      "matches": 3,
      "mismatches": [],
      "missing_boats": [],
      "extra_boats": [],
      "field_errors": [],
      "timestamp": "2025-10-17T03:28:42.556985"
    }
  ],
  "timestamp": "2025-10-17T03:28:42.557525"
}