{
  "date_range": {
    "start": "2025-06-01",
    "end": "2025-10-23"
  },
  "summary": {
    "total_dates": 145,
    "passed": 145,
    "failed": 0,
    "errors": 0,
    "skipped": 0,
    "effective_dates": 145,
    "pass_rate": 100.0
  },
  "reports": [
    {
      "date": "2025-06-01",
      "status": "PASS",
      "source_boat_count": 34,
      "database_boat_count": 34,
      "matches": 34,
      "mismatches": [],
      "missing_boats": [],
      "extra_boats": [],
      "field_errors": [],
      "timestamp": "2025-10-24T14:57:30.539495"
    },
    {
      "date": "2025-06-02",
      "status": "PASS",
      "source_boat_count": 16,
      "database_boat_count": 16,
      "matches": 16,
      "mismatches": [],
      "missing_boats": [],
      "extra_boats": [],
      "field_errors": [],
      "timestamp": "2025-10-24T14:57:32.951319"
    },
    {
      "date": "2025-06-03",
      "status": "PASS",
      "source_boat_count": 13,
      "database_boat_count": 13,
      "matches": 13,
      "mismatches": [],
      "missing_boats": [],
      "extra_boats": [],
      "field_errors": [],
      "timestamp": "2025-10-24T14:57:35.402304"
    },
    {
      "date": "2025-06-04",
      "status": "PASS",
      "source_boat_count": 20,
      "database_boat_count": 20,
      "matches": 20,
      "mismatches": [],
      "missing_boats": [],
      "extra_boats": [],
      "field_errors": [],
      "timestamp": "2025-10-24T14:57:37.768175"
    },
    {
      "date": "2025-06-05",
      "status": "PASS",
      "source_boat_count": 19,
      "database_boat_count": 19,
      "matches": 19,
      "mismatches": [],
      "missing_boats": [],
      "extra_boats": [],
      "field_errors": [],
      "timestamp": "2025-10-24T14:57:40.231156"
    },
    {
      "date": "2025-06-06",
      "status": "PASS",
      "source_boat_count": 27,
      "database_boat_count": 27,
      "matches": 27,
      "mismatches": [],
      "missing_boats": [],
      "extra_boats": [],
      "field_errors": [],
      "timestamp": "2025-10-24T14:57:42.633896"
    },
    {
      "date": "2025-06-07",
      "status": "PASS",
      "source_boat_count": 36,
      "database_boat_count": 36,
      "matches": 36,
      "mismatches": [],
      "missing_boats": [],
      "extra_boats": [],
      "field_errors": [],
      "timestamp": "2025-10-24T14:57:45.057761"
    },
    {
      "date": "2025-06-08",
      "status": "PASS",
      "source_boat_count": 35,
      "database_boat_count": 35,
      "matches": 35,
      "mismatches": [],
      "missing_boats": [],
      "extra_boats": [],
      "field_errors": [],
      "timestamp": "2025-10-24T14:57:47.514059"
    },
    {
      "date": "2025-06-09",
      "status": "PASS",
      "source_boat_count": 20,
      "database_boat_count": 20,
      "matches": 20,
      "mismatches": [],
      "missing_boats": [],
      "extra_boats": [],
      "field_errors": [],
      "timestamp": "2025-10-24T14:57:49.895415"
    },
    {
      "date": "2025-06-10",
      "status": "PASS",
      "source_boat_count": 22,
      "database_boat_count": 22,
      "matches": 22,
      "mismatches": [],
      "missing_boats": [],
      "extra_boats": [],
      "field_errors": [],
      "timestamp": "2025-10-24T14:57:52.346965"
    },
    {
      "date": "2025-06-11",
      "status": "PASS",
      "source_boat_count": 23,
      "database_boat_count": 23,
      "matches": 23,
      "mismatches": [],
      "missing_boats": [],
      "extra_boats": [],
      "field_errors": [],
      "timestamp": "2025-10-24T14:57:54.716514"
    },
    {
      "date": "2025-06-12",
      "status": "PASS",
      "source_boat_count": 23,
      "database_boat_count": 23,
      "matches": 23,
      "mismatches": [],
      "missing_boats": [],
      "extra_boats": [],
      "field_errors": [],
      "timestamp": "2025-10-24T14:57:57.086514"
    },
    {
      "date": "2025-06-13",
      "status": "PASS",
      "source_boat_count": 27,
      "database_boat_count": 27,
      "matches": 27,
      "mismatches": [],
      "missing_boats": [],
      "extra_boats": [],
      "field_errors": [],
      "timestamp": "2025-10-24T14:57:59.446812"
    },
    {
      "date": "2025-06-14",
      "status": "PASS",
      "source_boat_count": 46,
      "database_boat_count": 46,
      "matches": 46,
      "mismatches": [],
      "missing_boats": [],
      "extra_boats": [],
      "field_errors": [],
      "timestamp": "2025-10-24T14:58:01.828074"
    },
    {
      "date": "2025-06-15",
      "status": "PASS",
      "source_boat_count": 44,
      "database_boat_count": 44,
      "matches": 44,
      "mismatches": [],
      "missing_boats": [],
      "extra_boats": [],
      "field_errors": [],
      "timestamp": "2025-10-24T14:58:04.233204"
    },
    {
      "date": "2025-06-16",
      "status": "PASS",
      "source_boat_count": 28,
      "database_boat_count": 28,
      "matches": 28,
      "mismatches": [],
      "missing_boats": [],
      "extra_boats": [],
      "field_errors": [],
      "timestamp": "2025-10-24T14:58:06.585553"
    },
    {
      "date": "2025-06-17",
      "status": "PASS",
      "source_boat_count": 24,
      "database_boat_count": 24,
      "matches": 24,
      "mismatches": [],
      "missing_boats": [],
      "extra_boats": [],
      "field_errors": [],
      "timestamp": "2025-10-24T14:58:09.033937"
    },
    {
      "date": "2025-06-18",
      "status": "PASS",
      "source_boat_count": 29,
      "database_boat_count": 29,
      "matches": 29,
      "mismatches": [],
      "missing_boats": [],
      "extra_boats": [],
      "field_errors": [],
      "timestamp": "2025-10-24T14:58:11.490497"
    },
    {
      "date": "2025-06-19",
      "status": "PASS",
      "source_boat_count": 33,
      "database_boat_count": 33,
      "matches": 33,
      "mismatches": [],
      "missing_boats": [],
      "extra_boats": [],
      "field_errors": [],
      "timestamp": "2025-10-24T14:58:13.866495"
    },
    {
      "date": "2025-06-20",
      "status": "PASS",
      "source_boat_count": 33,
      "database_boat_count": 33,
      "matches": 33,
      "mismatches": [],
      "missing_boats": [],
      "extra_boats": [],
      "field_errors": [],
      "timestamp": "2025-10-24T14:58:16.250389"
    },
    {
      "date": "2025-06-21",
      "status": "PASS",
      "source_boat_count": 36,
      "database_boat_count": 36,
      "matches": 36,
      "mismatches": [],
      "missing_boats": [],
      "extra_boats": [],
      "field_errors": [],
      "timestamp": "2025-10-24T14:58:18.616275"
    },
    {
      "date": "2025-06-22",
      "status": "PASS",
      "source_boat_count": 33,
      "database_boat_count": 33,
      "matches": 33,
      "mismatches": [],
      "missing_boats": [],
      "extra_boats": [],
      "field_errors": [],
      "timestamp": "2025-10-24T14:58:20.993331"
    },
    {
      "date": "2025-06-23",
      "status": "PASS",
      "source_boat_count": 34,
      "database_boat_count": 34,
      "matches": 34,
      "mismatches": [],
      "missing_boats": [],
      "extra_boats": [],
      "field_errors": [],
      "timestamp": "2025-10-24T14:58:23.419016"
    },
    {
      "date": "2025-06-24",
      "status": "PASS",
      "source_boat_count": 30,
      "database_boat_count": 30,
      "matches": 30,
      "mismatches": [],
      "missing_boats": [],
      "extra_boats": [],
      "field_errors": [],
      "timestamp": "2025-10-24T14:58:25.793833"
    },
    {
      "date": "2025-06-25",
      "status": "PASS",
      "source_boat_count": 32,
      "database_boat_count": 32,
      "matches": 32,
      "mismatches": [],
      "missing_boats": [],
      "extra_boats": [],
      "field_errors": [],
      "timestamp": "2025-10-24T14:58:28.249494"
    },
    {
      "date": "2025-06-26",
      "status": "PASS",
      "source_boat_count": 31,
      "database_boat_count": 31,
      "matches": 31,
      "mismatches": [],
      "missing_boats": [],
      "extra_boats": [],
      "field_errors": [],
      "timestamp": "2025-10-24T14:58:30.654255"
    },
    {
      "date": "2025-06-27",
      "status": "PASS",
      "source_boat_count": 42,
      "database_boat_count": 42,
      "matches": 42,
      "mismatches": [],
      "missing_boats": [],
      "extra_boats": [],
      "field_errors": [],
      "timestamp": "2025-10-24T14:58:33.080648"
    },
    {
      "date": "2025-06-28",
      "status": "PASS",
      "source_boat_count": 48,
      "database_boat_count": 48,
      "matches": 48,
      "mismatches": [],
      "missing_boats": [],
      "extra_boats": [],
      "field_errors": [],
      "timestamp": "2025-10-24T14:58:35.486961"
    },
    {
      "date": "2025-06-29",
      "status": "PASS",
      "source_boat_count": 37,
      "database_boat_count": 37,
      "matches": 37,
      "mismatches": [],
      "missing_boats": [],
      "extra_boats": [],
      "field_errors": [],
      "timestamp": "2025-10-24T14:58:38.011281"
    },
    {
      "date": "2025-06-30",
      "status": "PASS",
      "source_boat_count": 24,
      "database_boat_count": 24,
      "matches": 24,
      "mismatches": [],
      "missing_boats": [],
      "extra_boats": [],
      "field_errors": [],
      "timestamp": "2025-10-24T14:58:40.354926"
    },
    {
      "date": "2025-07-01",
      "status": "PASS",
      "source_boat_count": 28,
      "database_boat_count": 28,
      "matches": 28,
      "mismatches": [],
      "missing_boats": [],
      "extra_boats": [],
      "field_errors": [],
      "timestamp": "2025-10-24T14:58:42.917832"
    },
    {
      "date": "2025-07-02",
      "status": "PASS",
      "source_boat_count": 27,
      "database_boat_count": 27,
      "matches": 27,
      "mismatches": [],
      "missing_boats": [],
      "extra_boats": [],
      "field_errors": [],
      "timestamp": "2025-10-24T14:58:45.562747"
    },
    {
      "date": "2025-07-03",
      "status": "PASS",
      "source_boat_count": 26,
      "database_boat_count": 26,
      "matches": 26,
      "mismatches": [],
      "missing_boats": [],
      "extra_boats": [],
      "field_errors": [],
      "timestamp": "2025-10-24T14:58:48.146054"
    },
    {
      "date": "2025-07-04",
      "status": "PASS",
      "source_boat_count": 24,
      "database_boat_count": 24,
      "matches": 24,
      "mismatches": [],
      "missing_boats": [],
      "extra_boats": [],
      "field_errors": [],
      "timestamp": "2025-10-24T14:58:50.683327"
    },
    {
      "date": "2025-07-05",
      "status": "PASS",
      "source_boat_count": 40,
      "database_boat_count": 40,
      "matches": 40,
      "mismatches": [],
      "missing_boats": [],
      "extra_boats": [],
      "field_errors": [],
      "timestamp": "2025-10-24T14:58:53.068299"
    },
    {
      "date": "2025-07-06",
      "status": "PASS",
      "source_boat_count": 41,
      "database_boat_count": 41,
      "matches": 41,
      "mismatches": [],
      "missing_boats": [],
      "extra_boats": [],
      "field_errors": [],
      "timestamp": "2025-10-24T14:58:55.450022"
    },
    {
      "date": "2025-07-07",
      "status": "PASS",
      "source_boat_count": 23,
      "database_boat_count": 23,
      "matches": 23,
      "mismatches": [],
      "missing_boats": [],
      "extra_boats": [],
      "field_errors": [],
      "timestamp": "2025-10-24T14:58:57.799036"
    },
    {
      "date": "2025-07-08",
      "status": "PASS",
      "source_boat_count": 24,
      "database_boat_count": 24,
      "matches": 24,
      "mismatches": [],
      "missing_boats": [],
      "extra_boats": [],
      "field_errors": [],
      "timestamp": "2025-10-24T14:59:00.143498"
    },
    {
      "date": "2025-07-09",
      "status": "PASS",
      "source_boat_count": 20,
      "database_boat_count": 20,
      "matches": 20,
      "mismatches": [],
      "missing_boats": [],
      "extra_boats": [],
      "field_errors": [],
      "timestamp": "2025-10-24T14:59:02.503942"
    },
    {
      "date": "2025-07-10",
      "status": "PASS",
      "source_boat_count": 30,
      "database_boat_count": 30,
      "matches": 30,
      "mismatches": [],
      "missing_boats": [],
      "extra_boats": [],
      "field_errors": [],
      "timestamp": "2025-10-24T14:59:05.067005"
    },
    {
      "date": "2025-07-11",
      "status": "PASS",
      "source_boat_count": 35,
      "database_boat_count": 35,
      "matches": 35,
      "mismatches": [],
      "missing_boats": [],
      "extra_boats": [],
      "field_errors": [],
      "timestamp": "2025-10-24T14:59:07.626249"
    },
    {
      "date": "2025-07-12",
      "status": "PASS",
      "source_boat_count": 33,
      "database_boat_count": 33,
      "matches": 33,
      "mismatches": [],
      "missing_boats": [],
      "extra_boats": [],
      "field_errors": [],
      "timestamp": "2025-10-24T14:59:10.198063"
    },
    {
      "date": "2025-07-13",
      "status": "PASS",
      "source_boat_count": 37,
      "database_boat_count": 37,
      "matches": 37,
      "mismatches": [],
      "missing_boats": [],
      "extra_boats": [],
      "field_errors": [],
      "timestamp": "2025-10-24T14:59:12.756016"
    },
    {
      "date": "2025-07-14",
      "status": "PASS",
      "source_boat_count": 32,
      "database_boat_count": 32,
      "matches": 32,
      "mismatches": [],
      "missing_boats": [],
      "extra_boats": [],
      "field_errors": [],
      "timestamp": "2025-10-24T14:59:15.306943"
    },
    {
      "date": "2025-07-15",
      "status": "PASS",
      "source_boat_count": 26,
      "database_boat_count": 26,
      "matches": 26,
      "mismatches": [],
      "missing_boats": [],
      "extra_boats": [],
      "field_errors": [],
      "timestamp": "2025-10-24T14:59:17.854841"
    },
    {
      "date": "2025-07-16",
      "status": "PASS",
      "source_boat_count": 29,
      "database_boat_count": 29,
      "matches": 29,
      "mismatches": [],
      "missing_boats": [],
      "extra_boats": [],
      "field_errors": [],
      "timestamp": "2025-10-24T14:59:20.429973"
    },
    {
      "date": "2025-07-17",
      "status": "PASS",
      "source_boat_count": 34,
      "database_boat_count": 34,
      "matches": 34,
      "mismatches": [],
      "missing_boats": [],
      "extra_boats": [],
      "field_errors": [],
      "timestamp": "2025-10-24T14:59:22.984071"
    },
    {
      "date": "2025-07-18",
      "status": "PASS",
      "source_boat_count": 41,
      "database_boat_count": 41,
      "matches": 41,
      "mismatches": [],
      "missing_boats": [],
      "extra_boats": [],
      "field_errors": [],
      "timestamp": "2025-10-24T14:59:25.537747"
    },
    {
      "date": "2025-07-19",
      "status": "PASS",
      "source_boat_count": 44,
      "database_boat_count": 44,
      "matches": 44,
      "mismatches": [],
      "missing_boats": [],
      "extra_boats": [],
      "field_errors": [],
      "timestamp": "2025-10-24T14:59:28.160254"
    },
    {
      "date": "2025-07-20",
      "status": "PASS",
      "source_boat_count": 30,
      "database_boat_count": 30,
      "matches": 30,
      "mismatches": [],
      "missing_boats": [],
      "extra_boats": [],
      "field_errors": [],
      "timestamp": "2025-10-24T14:59:30.570324"
    },
    {
      "date": "2025-07-21",
      "status": "PASS",
      "source_boat_count": 33,
      "database_boat_count": 33,
      "matches": 33,
      "mismatches": [],
      "missing_boats": [],
      "extra_boats": [],
      "field_errors": [],
      "timestamp": "2025-10-24T14:59:32.943176"
    },
    {
      "date": "2025-07-22",
      "status": "PASS",
      "source_boat_count": 26,
      "database_boat_count": 26,
      "matches": 26,
      "mismatches": [],
      "missing_boats": [],
      "extra_boats": [],
      "field_errors": [],
      "timestamp": "2025-10-24T14:59:35.396565"
    },
    {
      "date": "2025-07-23",
      "status": "PASS",
      "source_boat_count": 30,
      "database_boat_count": 30,
      "matches": 30,
      "mismatches": [],
      "missing_boats": [],
      "extra_boats": [],
      "field_errors": [],
      "timestamp": "2025-10-24T14:59:37.760814"
    },
    {
      "date": "2025-07-24",
      "status": "PASS",
      "source_boat_count": 27,
      "database_boat_count": 27,
      "matches": 27,
      "mismatches": [],
      "missing_boats": [],
      "extra_boats": [],
      "field_errors": [],
      "timestamp": "2025-10-24T14:59:40.141710"
    },
    {
      "date": "2025-07-25",
      "status": "PASS",
      "source_boat_count": 26,
      "database_boat_count": 26,
      "matches": 26,
      "mismatches": [],
      "missing_boats": [],
      "extra_boats": [],
      "field_errors": [],
      "timestamp": "2025-10-24T14:59:42.614391"
    },
    {
      "date": "2025-07-26",
      "status": "PASS",
      "source_boat_count": 39,
      "database_boat_count": 39,
      "matches": 39,
      "mismatches": [],
      "missing_boats": [],
      "extra_boats": [],
      "field_errors": [],
      "timestamp": "2025-10-24T14:59:45.016263"
    },
    {
      "date": "2025-07-27",
      "status": "PASS",
      "source_boat_count": 46,
      "database_boat_count": 46,
      "matches": 46,
      "mismatches": [],
      "missing_boats": [],
      "extra_boats": [],
      "field_errors": [],
      "timestamp": "2025-10-24T14:59:47.398132"
    },
    {
      "date": "2025-07-28",
      "status": "PASS",
      "source_boat_count": 24,
      "database_boat_count": 24,
      "matches": 24,
      "mismatches": [],
      "missing_boats": [],
      "extra_boats": [],
      "field_errors": [],
      "timestamp": "2025-10-24T14:59:49.925717"
    },
    {
      "date": "2025-07-29",
      "status": "PASS",
      "source_boat_count": 25,
      "database_boat_count": 25,
      "matches": 25,
      "mismatches": [],
      "missing_boats": [],
      "extra_boats": [],
      "field_errors": [],
      "timestamp": "2025-10-24T14:59:52.512098"
    },
    {
      "date": "2025-07-30",
      "status": "PASS",
      "source_boat_count": 19,
      "database_boat_count": 19,
      "matches": 19,
      "mismatches": [],
      "missing_boats": [],
      "extra_boats": [],
      "field_errors": [],
      "timestamp": "2025-10-24T14:59:55.054846"
    },
    {
      "date": "2025-07-31",
      "status": "PASS",
      "source_boat_count": 25,
      "database_boat_count": 25,
      "matches": 25,
      "mismatches": [],
      "missing_boats": [],
      "extra_boats": [],
      "field_errors": [],
      "timestamp": "2025-10-24T14:59:57.627684"
    },
    {
      "date": "2025-08-01",
      "status": "PASS",
      "source_boat_count": 36,
      "database_boat_count": 36,
      "matches": 36,
      "mismatches": [],
      "missing_boats": [],
      "extra_boats": [],
      "field_errors": [],
      "timestamp": "2025-10-24T15:00:00.280364"
    },
    {
      "date": "2025-08-02",
      "status": "PASS",
      "source_boat_count": 40,
      "database_boat_count": 40,
      "matches": 40,
      "mismatches": [],
      "missing_boats": [],
      "extra_boats": [],
      "field_errors": [],
      "timestamp": "2025-10-24T15:00:02.883531"
    },
    {
      "date": "2025-08-03",
      "status": "PASS",
      "source_boat_count": 34,
      "database_boat_count": 34,
      "matches": 34,
      "mismatches": [],
      "missing_boats": [],
      "extra_boats": [],
      "field_errors": [],
      "timestamp": "2025-10-24T15:00:05.462867"
    },
    {
      "date": "2025-08-04",
      "status": "PASS",
      "source_boat_count": 19,
      "database_boat_count": 19,
      "matches": 19,
      "mismatches": [],
      "missing_boats": [],
      "extra_boats": [],
      "field_errors": [],
      "timestamp": "2025-10-24T15:00:08.033515"
    },
    {
      "date": "2025-08-05",
      "status": "PASS",
      "source_boat_count": 28,
      "database_boat_count": 28,
      "matches": 28,
      "mismatches": [],
      "missing_boats": [],
      "extra_boats": [],
      "field_errors": [],
      "timestamp": "2025-10-24T15:00:10.659103"
    },
    {
      "date": "2025-08-06",
      "status": "PASS",
      "source_boat_count": 32,
      "database_boat_count": 32,
      "matches": 32,
      "mismatches": [],
      "missing_boats": [],
      "extra_boats": [],
      "field_errors": [],
      "timestamp": "2025-10-24T15:00:13.227736"
    },
    {
      "date": "2025-08-07",
      "status": "PASS",
      "source_boat_count": 24,
      "database_boat_count": 24,
      "matches": 24,
      "mismatches": [],
      "missing_boats": [],
      "extra_boats": [],
      "field_errors": [],
      "timestamp": "2025-10-24T15:00:15.790772"
    },
    {
      "date": "2025-08-08",
      "status": "PASS",
      "source_boat_count": 37,
      "database_boat_count": 37,
      "matches": 37,
      "mismatches": [],
      "missing_boats": [],
      "extra_boats": [],
      "field_errors": [],
      "timestamp": "2025-10-24T15:00:18.353550"
    },
    {
      "date": "2025-08-09",
      "status": "PASS",
      "source_boat_count": 48,
      "database_boat_count": 48,
      "matches": 48,
      "mismatches": [],
      "missing_boats": [],
      "extra_boats": [],
      "field_errors": [],
      "timestamp": "2025-10-24T15:00:21.053923"
    },
    {
      "date": "2025-08-10",
      "status": "PASS",
      "source_boat_count": 41,
      "database_boat_count": 41,
      "matches": 41,
      "mismatches": [],
      "missing_boats": [],
      "extra_boats": [],
      "field_errors": [],
      "timestamp": "2025-10-24T15:00:23.686070"
    },
    {
      "date": "2025-08-11",
      "status": "PASS",
      "source_boat_count": 29,
      "database_boat_count": 29,
      "matches": 29,
      "mismatches": [],
      "missing_boats": [],
      "extra_boats": [],
      "field_errors": [],
      "timestamp": "2025-10-24T15:00:26.256783"
    },
    {
      "date": "2025-08-12",
      "status": "PASS",
      "source_boat_count": 22,
      "database_boat_count": 22,
      "matches": 22,
      "mismatches": [],
      "missing_boats": [],
      "extra_boats": [],
      "field_errors": [],
      "timestamp": "2025-10-24T15:00:28.814166"
    },
    {
      "date": "2025-08-13",
      "status": "PASS",
      "source_boat_count": 28,
      "database_boat_count": 28,
      "matches": 28,
      "mismatches": [],
      "missing_boats": [],
      "extra_boats": [],
      "field_errors": [],
      "timestamp": "2025-10-24T15:00:31.338828"
    },
    {
      "date": "2025-08-14",
      "status": "PASS",
      "source_boat_count": 27,
      "database_boat_count": 27,
      "matches": 27,
      "mismatches": [],
      "missing_boats": [],
      "extra_boats": [],
      "field_errors": [],
      "timestamp": "2025-10-24T15:00:33.917267"
    },
    {
      "date": "2025-08-15",
      "status": "PASS",
      "source_boat_count": 36,
      "database_boat_count": 36,
      "matches": 36,
      "mismatches": [],
      "missing_boats": [],
      "extra_boats": [],
      "field_errors": [],
      "timestamp": "2025-10-24T15:00:36.465985"
    },
    {
      "date": "2025-08-16",
      "status": "PASS",
      "source_boat_count": 45,
      "database_boat_count": 45,
      "matches": 45,
      "mismatches": [],
      "missing_boats": [],
      "extra_boats": [],
      "field_errors": [],
      "timestamp": "2025-10-24T15:00:39.076573"
    },
    {
      "date": "2025-08-17",
      "status": "PASS",
      "source_boat_count": 41,
      "database_boat_count": 41,
      "matches": 41,
      "mismatches": [],
      "missing_boats": [],
      "extra_boats": [],
      "field_errors": [],
      "timestamp": "2025-10-24T15:00:41.672504"
    },
    {
      "date": "2025-08-18",
      "status": "PASS",
      "source_boat_count": 25,
      "database_boat_count": 25,
      "matches": 25,
      "mismatches": [],
      "missing_boats": [],
      "extra_boats": [],
      "field_errors": [],
      "timestamp": "2025-10-24T15:00:44.257517"
    },
    {
      "date": "2025-08-19",
      "status": "PASS",
      "source_boat_count": 21,
      "database_boat_count": 21,
      "matches": 21,
      "mismatches": [],
      "missing_boats": [],
      "extra_boats": [],
      "field_errors": [],
      "timestamp": "2025-10-24T15:00:46.815108"
    },
    {
      "date": "2025-08-20",
      "status": "PASS",
      "source_boat_count": 20,
      "database_boat_count": 20,
      "matches": 20,
      "mismatches": [],
      "missing_boats": [],
      "extra_boats": [],
      "field_errors": [],
      "timestamp": "2025-10-24T15:00:49.431915"
    },
    {
      "date": "2025-08-21",
      "status": "PASS",
      "source_boat_count": 32,
      "database_boat_count": 32,
      "matches": 32,
      "mismatches": [],
      "missing_boats": [],
      "extra_boats": [],
      "field_errors": [],
      "timestamp": "2025-10-24T15:00:51.993307"
    },
    {
      "date": "2025-08-22",
      "status": "PASS",
      "source_boat_count": 25,
      "database_boat_count": 25,
      "matches": 25,
      "mismatches": [],
      "missing_boats": [],
      "extra_boats": [],
      "field_errors": [],
      "timestamp": "2025-10-24T15:00:54.545177"
    },
    {
      "date": "2025-08-23",
      "status": "PASS",
      "source_boat_count": 47,
      "database_boat_count": 47,
      "matches": 47,
      "mismatches": [],
      "missing_boats": [],
      "extra_boats": [],
      "field_errors": [],
      "timestamp": "2025-10-24T15:00:57.168608"
    },
    {
      "date": "2025-08-24",
      "status": "PASS",
      "source_boat_count": 42,
      "database_boat_count": 42,
      "matches": 42,
      "mismatches": [],
      "missing_boats": [],
      "extra_boats": [],
      "field_errors": [],
      "timestamp": "2025-10-24T15:00:59.749920"
    },
    {
      "date": "2025-08-25",
      "status": "PASS",
      "source_boat_count": 24,
      "database_boat_count": 24,
      "matches": 24,
      "mismatches": [],
      "missing_boats": [],
      "extra_boats": [],
      "field_errors": [],
      "timestamp": "2025-10-24T15:01:02.321084"
    },
    {
      "date": "2025-08-26",
      "status": "PASS",
      "source_boat_count": 19,
      "database_boat_count": 19,
      "matches": 19,
      "mismatches": [],
      "missing_boats": [],
      "extra_boats": [],
      "field_errors": [],
      "timestamp": "2025-10-24T15:01:04.878279"
    },
    {
      "date": "2025-08-27",
      "status": "PASS",
      "source_boat_count": 14,
      "database_boat_count": 14,
      "matches": 14,
      "mismatches": [],
      "missing_boats": [],
      "extra_boats": [],
      "field_errors": [],
      "timestamp": "2025-10-24T15:01:07.395923"
    },
    {
      "date": "2025-08-28",
      "status": "PASS",
      "source_boat_count": 20,
      "database_boat_count": 20,
      "matches": 20,
      "mismatches": [],
      "missing_boats": [],
      "extra_boats": [],
      "field_errors": [],
      "timestamp": "2025-10-24T15:01:09.935258"
    },
    {
      "date": "2025-08-29",
      "status": "PASS",
      "source_boat_count": 34,
      "database_boat_count": 34,
      "matches": 34,
      "mismatches": [],
      "missing_boats": [],
      "extra_boats": [],
      "field_errors": [],
      "timestamp": "2025-10-24T15:01:12.500689"
    },
    {
      "date": "2025-08-30",
      "status": "PASS",
      "source_boat_count": 42,
      "database_boat_count": 42,
      "matches": 42,
      "mismatches": [],
      "missing_boats": [],
      "extra_boats": [],
      "field_errors": [],
      "timestamp": "2025-10-24T15:01:15.127940"
    },
    {
      "date": "2025-08-31",
      "status": "PASS",
      "source_boat_count": 35,
      "database_boat_count": 35,
      "matches": 35,
      "mismatches": [],
      "missing_boats": [],
      "extra_boats": [],
      "field_errors": [],
      "timestamp": "2025-10-24T15:01:17.728374"
    },
    {
      "date": "2025-09-01",
      "status": "PASS",
      "source_boat_count": 37,
      "database_boat_count": 37,
      "matches": 37,
      "mismatches": [],
      "missing_boats": [],
      "extra_boats": [],
      "field_errors": [],
      "timestamp": "2025-10-24T15:01:20.090108"
    },
    {
      "date": "2025-09-02",
      "status": "PASS",
      "source_boat_count": 11,
      "database_boat_count": 11,
      "matches": 11,
      "mismatches": [],
      "missing_boats": [],
      "extra_boats": [],
      "field_errors": [],
      "timestamp": "2025-10-24T15:01:22.614304"
    },
    {
      "date": "2025-09-03",
      "status": "PASS",
      "source_boat_count": 13,
      "database_boat_count": 13,
      "matches": 13,
      "mismatches": [],
      "missing_boats": [],
      "extra_boats": [],
      "field_errors": [],
      "timestamp": "2025-10-24T15:01:25.144683"
    },
    {
      "date": "2025-09-04",
      "status": "PASS",
      "source_boat_count": 17,
      "database_boat_count": 17,
      "matches": 17,
      "mismatches": [],
      "missing_boats": [],
      "extra_boats": [],
      "field_errors": [],
      "timestamp": "2025-10-24T15:01:27.808996"
    },
    {
      "date": "2025-09-05",
      "status": "PASS",
      "source_boat_count": 24,
      "database_boat_count": 24,
      "matches": 24,
      "mismatches": [],
      "missing_boats": [],
      "extra_boats": [],
      "field_errors": [],
      "timestamp": "2025-10-24T15:01:30.374913"
    },
    {
      "date": "2025-09-06",
      "status": "PASS",
      "source_boat_count": 33,
      "database_boat_count": 33,
      "matches": 33,
      "mismatches": [],
      "missing_boats": [],
      "extra_boats": [],
      "field_errors": [],
      "timestamp": "2025-10-24T15:01:32.924110"
    },
    {
      "date": "2025-09-07",
      "status": "PASS",
      "source_boat_count": 32,
      "database_boat_count": 32,
      "matches": 32,
      "mismatches": [],
      "missing_boats": [],
      "extra_boats": [],
      "field_errors": [],
      "timestamp": "2025-10-24T15:01:35.501508"
    },
    {
      "date": "2025-09-08",
      "status": "PASS",
      "source_boat_count": 13,
      "database_boat_count": 13,
      "matches": 13,
      "mismatches": [],
      "missing_boats": [],
      "extra_boats": [],
      "field_errors": [],
      "timestamp": "2025-10-24T15:01:38.043078"
    },
    {
      "date": "2025-09-09",
      "status": "PASS",
      "source_boat_count": 15,
      "database_boat_count": 15,
      "matches": 15,
      "mismatches": [],
      "missing_boats": [],
      "extra_boats": [],
      "field_errors": [],
      "timestamp": "2025-10-24T15:01:40.544873"
    },
    {
      "date": "2025-09-10",
      "status": "PASS",
      "source_boat_count": 12,
      "database_boat_count": 12,
      "matches": 12,
      "mismatches": [],
      "missing_boats": [],
      "extra_boats": [],
      "field_errors": [],
      "timestamp": "2025-10-24T15:01:43.077964"
    },
    {
      "date": "2025-09-11",
      "status": "PASS",
      "source_boat_count": 15,
      "database_boat_count": 15,
      "matches": 15,
      "mismatches": [],
      "missing_boats": [],
      "extra_boats": [],
      "field_errors": [],
      "timestamp": "2025-10-24T15:01:46.021123"
    },
    {
      "date": "2025-09-12",
      "status": "PASS",
      "source_boat_count": 30,
      "database_boat_count": 30,
      "matches": 30,
      "mismatches": [],
      "missing_boats": [],
      "extra_boats": [],
      "field_errors": [],
      "timestamp": "2025-10-24T15:01:48.595741"
    },
    {
      "date": "2025-09-13",
      "status": "PASS",
      "source_boat_count": 36,
      "database_boat_count": 36,
      "matches": 36,
      "mismatches": [],
      "missing_boats": [],
      "extra_boats": [],
      "field_errors": [],
      "timestamp": "2025-10-24T15:01:51.240309"
    },
    {
      "date": "2025-09-14",
      "status": "PASS",
      "source_boat_count": 32,
      "database_boat_count": 32,
      "matches": 32,
      "mismatches": [],
      "missing_boats": [],
      "extra_boats": [],
      "field_errors": [],
      "timestamp": "2025-10-24T15:01:53.780935"
    },
    {
      "date": "2025-09-15",
      "status": "PASS",
      "source_boat_count": 15,
      "database_boat_count": 15,
      "matches": 15,
      "mismatches": [],
      "missing_boats": [],
      "extra_boats": [],
      "field_errors": [],
      "timestamp": "2025-10-24T15:01:56.322530"
    },
    {
      "date": "2025-09-16",
      "status": "PASS",
      "source_boat_count": 14,
      "database_boat_count": 14,
      "matches": 14,
      "mismatches": [],
      "missing_boats": [],
      "extra_boats": [],
      "field_errors": [],
      "timestamp": "2025-10-24T15:01:58.903431"
    },
    {
      "date": "2025-09-17",
      "status": "PASS",
      "source_boat_count": 16,
      "database_boat_count": 16,
      "matches": 16,
      "mismatches": [],
      "missing_boats": [],
      "extra_boats": [],
      "field_errors": [],
      "timestamp": "2025-10-24T15:02:01.642194"
    },
    {
      "date": "2025-09-18",
      "status": "PASS",
      "source_boat_count": 10,
      "database_boat_count": 10,
      "matches": 10,
      "mismatches": [],
      "missing_boats": [],
      "extra_boats": [],
      "field_errors": [],
      "timestamp": "2025-10-24T15:02:04.259630"
    },
    {
      "date": "2025-09-19",
      "status": "PASS",
      "source_boat_count": 30,
      "database_boat_count": 30,
      "matches": 30,
      "mismatches": [],
      "missing_boats": [],
      "extra_boats": [],
      "field_errors": [],
      "timestamp": "2025-10-24T15:02:06.820536"
    },
    {
      "date": "2025-09-20",
      "status": "PASS",
      "source_boat_count": 36,
      "database_boat_count": 36,
      "matches": 36,
      "mismatches": [],
      "missing_boats": [],
      "extra_boats": [],
      "field_errors": [],
      "timestamp": "2025-10-24T15:02:09.552225"
    },
    {
      "date": "2025-09-21",
      "status": "PASS",
      "source_boat_count": 34,
      "database_boat_count": 34,
      "matches": 34,
      "mismatches": [],
      "missing_boats": [],
      "extra_boats": [],
      "field_errors": [],
      "timestamp": "2025-10-24T15:02:12.204531"
    },
    {
      "date": "2025-09-22",
      "status": "PASS",
      "source_boat_count": 13,
      "database_boat_count": 13,
      "matches": 13,
      "mismatches": [],
      "missing_boats": [],
      "extra_boats": [],
      "field_errors": [],
      "timestamp": "2025-10-24T15:02:14.710832"
    },
    {
      "date": "2025-09-23",
      "status": "PASS",
      "source_boat_count": 13,
      "database_boat_count": 13,
      "matches": 13,
      "mismatches": [],
      "missing_boats": [],
      "extra_boats": [],
      "field_errors": [],
      "timestamp": "2025-10-24T15:02:17.301652"
    },
    {
      "date": "2025-09-24",
      "status": "PASS",
      "source_boat_count": 14,
      "database_boat_count": 14,
      "matches": 14,
      "mismatches": [],
      "missing_boats": [],
      "extra_boats": [],
      "field_errors": [],
      "timestamp": "2025-10-24T15:02:19.863177"
    },
    {
      "date": "2025-09-25",
      "status": "PASS",
      "source_boat_count": 17,
      "database_boat_count": 17,
      "matches": 17,
      "mismatches": [],
      "missing_boats": [],
      "extra_boats": [],
      "field_errors": [],
      "timestamp": "2025-10-24T15:02:22.513892"
    },
    {
      "date": "2025-09-26",
      "status": "PASS",
      "source_boat_count": 24,
      "database_boat_count": 24,
      "matches": 24,
      "mismatches": [],
      "missing_boats": [],
      "extra_boats": [],
      "field_errors": [],
      "timestamp": "2025-10-24T15:02:25.034638"
    },
    {
      "date": "2025-09-27",
      "status": "PASS",
      "source_boat_count": 36,
      "database_boat_count": 36,
      "matches": 36,
      "mismatches": [],
      "missing_boats": [],
      "extra_boats": [],
      "field_errors": [],
      "timestamp": "2025-10-24T15:02:27.584145"
    },
    {
      "date": "2025-09-28",
      "status": "PASS",
      "source_boat_count": 30,
      "database_boat_count": 30,
      "matches": 30,
      "mismatches": [],
      "missing_boats": [],
      "extra_boats": [],
      "field_errors": [],
      "timestamp": "2025-10-24T15:02:30.312972"
    },
    {
      "date": "2025-09-29",
      "status": "PASS",
      "source_boat_count": 10,
      "database_boat_count": 10,
      "matches": 10,
      "mismatches": [],
      "missing_boats": [],
      "extra_boats": [],
      "field_errors": [],
      "timestamp": "2025-10-24T15:02:32.874413"
    },
    {
      "date": "2025-09-30",
      "status": "PASS",
      "source_boat_count": 13,
      "database_boat_count": 13,
      "matches": 13,
      "mismatches": [],
      "missing_boats": [],
      "extra_boats": [],
      "field_errors": [],
      "timestamp": "2025-10-24T15:02:35.386186"
    },
    {
      "date": "2025-10-01",
      "status": "PASS",
      "source_boat_count": 16,
      "database_boat_count": 16,
      "matches": 16,
      "mismatches": [],
      "missing_boats": [],
      "extra_boats": [],
      "field_errors": [],
      "timestamp": "2025-10-24T15:02:37.947309"
    },
    {
      "date": "2025-10-02",
      "status": "PASS",
      "source_boat_count": 16,
      "database_boat_count": 16,
      "matches": 16,
      "mismatches": [],
      "missing_boats": [],
      "extra_boats": [],
      "field_errors": [],
      "timestamp": "2025-10-24T15:02:40.452236"
    },
    {
      "date": "2025-10-03",
      "status": "PASS",
      "source_boat_count": 15,
      "database_boat_count": 15,
      "matches": 15,
      "mismatches": [],
      "missing_boats": [],
      "extra_boats": [],
      "field_errors": [],
      "timestamp": "2025-10-24T15:02:45.235217"
    },
    {
      "date": "2025-10-04",
      "status": "PASS",
      "source_boat_count": 29,
      "database_boat_count": 29,
      "matches": 29,
      "mismatches": [],
      "missing_boats": [],
      "extra_boats": [],
      "field_errors": [],
      "timestamp": "2025-10-24T15:02:47.786497"
    },
    {
      "date": "2025-10-05",
      "status": "PASS",
      "source_boat_count": 24,
      "database_boat_count": 24,
      "matches": 24,
      "mismatches": [],
      "missing_boats": [],
      "extra_boats": [],
      "field_errors": [],
      "timestamp": "2025-10-24T15:02:50.313292"
    },
    {
      "date": "2025-10-06",
      "status": "PASS",
      "source_boat_count": 13,
      "database_boat_count": 13,
      "matches": 13,
      "mismatches": [],
      "missing_boats": [],
      "extra_boats": [],
      "field_errors": [],
      "timestamp": "2025-10-24T15:02:52.867885"
    },
    {
      "date": "2025-10-07",
      "status": "PASS",
      "source_boat_count": 12,
      "database_boat_count": 12,
      "matches": 12,
      "mismatches": [],
      "missing_boats": [],
      "extra_boats": [],
      "field_errors": [],
      "timestamp": "2025-10-24T15:02:55.432318"
    },
    {
      "date": "2025-10-08",
      "status": "PASS",
      "source_boat_count": 13,
      "database_boat_count": 13,
      "matches": 13,
      "mismatches": [],
      "missing_boats": [],
      "extra_boats": [],
      "field_errors": [],
      "timestamp": "2025-10-24T15:02:58.034898"
    },
    {
      "date": "2025-10-09",
      "status": "PASS",
      "source_boat_count": 11,
      "database_boat_count": 11,
      "matches": 11,
      "mismatches": [],
      "missing_boats": [],
      "extra_boats": [],
      "field_errors": [],
      "timestamp": "2025-10-24T15:03:00.577951"
    },
    {
      "date": "2025-10-10",
      "status": "PASS",
      "source_boat_count": 19,
      "database_boat_count": 19,
      "matches": 19,
      "mismatches": [],
      "missing_boats": [],
      "extra_boats": [],
      "field_errors": [],
      "timestamp": "2025-10-24T15:03:03.197293"
    },
    {
      "date": "2025-10-11",
      "status": "PASS",
      "source_boat_count": 19,
      "database_boat_count": 19,
      "matches": 19,
      "mismatches": [],
      "missing_boats": [],
      "extra_boats": [],
      "field_errors": [],
      "timestamp": "2025-10-24T15:03:05.743407"
    },
    {
      "date": "2025-10-12",
      "status": "PASS",
      "source_boat_count": 23,
      "database_boat_count": 23,
      "matches": 23,
      "mismatches": [],
      "missing_boats": [],
      "extra_boats": [],
      "field_errors": [],
      "timestamp": "2025-10-24T15:03:08.296081"
    },
    {
      "date": "2025-10-13",
      "status": "PASS",
      "source_boat_count": 6,
      "database_boat_count": 6,
      "matches": 6,
      "mismatches": [],
      "missing_boats": [],
      "extra_boats": [],
      "field_errors": [],
      "timestamp": "2025-10-24T15:03:10.821432"
    },
    {
      "date": "2025-10-14",
      "status": "PASS",
      "source_boat_count": 0,
      "database_boat_count": 0,
      "matches": 0,
      "mismatches": [],
      "missing_boats": [],
      "extra_boats": [],
      "field_errors": [],
      "timestamp": "2025-10-24T15:03:13.311282"
    },
    {
      "date": "2025-10-15",
      "status": "PASS",
      "source_boat_count": 10,
      "database_boat_count": 10,
      "matches": 10,
      "mismatches": [],
      "missing_boats": [],
      "extra_boats": [],
      "field_errors": [],
      "timestamp": "2025-10-24T15:03:15.891640"
    },
    {
      "date": "2025-10-16",
      "status": "PASS",
      "source_boat_count": 11,
      "database_boat_count": 11,
      "matches": 11,
      "mismatches": [],
      "missing_boats": [],
      "extra_boats": [],
      "field_errors": [],
      "timestamp": "2025-10-24T15:03:18.425015"
    },
    {
      "date": "2025-10-17",
      "status": "PASS",
      "source_boat_count": 22,
      "database_boat_count": 22,
      "matches": 22,
      "mismatches": [],
      "missing_boats": [],
      "extra_boats": [],
      "field_errors": [],
      "timestamp": "2025-10-24T15:03:20.960145"
    },
    {
      "date": "2025-10-18",
      "status": "PASS",
      "source_boat_count": 33,
      "database_boat_count": 33,
      "matches": 33,
      "mismatches": [],
      "missing_boats": [],
      "extra_boats": [],
      "field_errors": [],
      "timestamp": "2025-10-24T15:03:23.614890"
    },
    {
      "date": "2025-10-19",
      "status": "PASS",
      "source_boat_count": 28,
      "database_boat_count": 28,
      "matches": 28,
      "mismatches": [],
      "missing_boats": [],
      "extra_boats": [],
      "field_errors": [],
      "timestamp": "2025-10-24T15:03:25.993384"
    },
    {
      "date": "2025-10-20",
      "status": "PASS",
      "source_boat_count": 11,
      "database_boat_count": 11,
      "matches": 11,
      "mismatches": [],
      "missing_boats": [],
      "extra_boats": [],
      "field_errors": [],
      "timestamp": "2025-10-24T15:03:28.399364"
    },
    {
      "date": "2025-10-21",
      "status": "PASS",
      "source_boat_count": 10,
      "database_boat_count": 10,
      "matches": 10,
      "mismatches": [],
      "missing_boats": [],
      "extra_boats": [],
      "field_errors": [],
      "timestamp": "2025-10-24T15:03:30.724889"
    },
    {
      "date": "2025-10-22",
      "status": "PASS",
      "source_boat_count": 9,
      "database_boat_count": 9,
      "matches": 9,
      "mismatches": [],
      "missing_boats": [],
      "extra_boats": [],
      "field_errors": [],
      "timestamp": "2025-10-24T15:03:33.065566"
    },
    {
      "date": "2025-10-23",
      "status": "PASS",
      "source_boat_count": 11,
      "database_boat_count": 11,
      "matches": 11,
      "mismatches": [],
      "missing_boats": [],
      "extra_boats": [],
      "field_errors": [],
      "timestamp": "2025-10-24T15:03:35.432259"
    }
  ],
  "timestamp": "2025-10-24T15:03:35.432798"
}